lionherd/__init__.py
lionherd-1.0.0a0.dist-info/METADATA
lionherd-1.0.0a0.dist-info/WHEEL
lionherd-1.0.0a0.dist-info/licenses/LICENSE
lionherd-1.0.0a0.dist-info/RECORD
