Metadata-Version: 2.4
Name: lionherd
Version: 1.0.0a0
Summary: Core utilities, base classes, and protocols for lionherd ecosystem
License-File: LICENSE
Requires-Python: >=3.11
Requires-Dist: lionherd-core>=1.0.0a0
